Metadata-Version: 2.4
Name: stainx
Version: 0.0.21
Summary: Enhanced stain normalization for histopathology images with batch processing support. Optimized for CPU, GPU (CUDA), and MPS (Apple Silicon) devices.
Home-page: https://github.com/rendeirolab/stainx
Author: Samir Moustafa
Author-email: Yimin Zheng <yzheng@cemm.oeaw.ac.at>, Samir Moustafa <smoustafa@cemm.oeaw.ac.at>
License-Expression: GPL-3.0-or-later
Classifier: Environment :: GPU :: NVIDIA CUDA
Classifier: Intended Audience :: Developers
Classifier: Intended Audience :: Healthcare Industry
Classifier: Intended Audience :: Science/Research
Classifier: Programming Language :: Python :: 3
Classifier: Programming Language :: Python :: 3.11
Classifier: Programming Language :: Python :: 3.12
Classifier: Programming Language :: Python :: 3.13
Classifier: Topic :: Scientific/Engineering
Classifier: Topic :: Software Development
Requires-Python: >=3.11
Requires-Dist: torch>=2.0.0
Provides-Extra: cupy
Requires-Dist: cupy-cuda12x>=12.0.0; platform_machine != "arm64" and extra == "cupy"
Requires-Dist: cupy>=12.0.0; platform_machine == "arm64" and extra == "cupy"
Dynamic: author
Dynamic: home-page
Dynamic: requires-python
